<?xml version="1.0" encoding="UTF-8" standalone="yes" ?>
<bindings>
    <comment>
        // Copyright © Tanner Gooding and Contributors. Licensed under the MIT License (MIT). See License.md in the repository root for more information.
        
        // Ported from um/dwmapi.h in the Windows SDK for Windows 10.0.19041.0
        // Original source is Copyright © Microsoft. All rights reserved.
        
    </comment>
    <namespace name="TerraFX.Interop">
        <enumeration name="GESTURE_TYPE" access="public">
            <type>int</type>
            <enumerator name="GT_PEN_TAP" access="">
                <type primitive="False">int</type>
                <value>
                    <code>0
        </code>
                </value>
            </enumerator>
            <enumerator name="GT_PEN_DOUBLETAP" access="">
                <type primitive="False">int</type>
                <value>
                    <code>1
        </code>
                </value>
            </enumerator>
            <enumerator name="GT_PEN_RIGHTTAP" access="">
                <type primitive="False">int</type>
                <value>
                    <code>2
        </code>
                </value>
            </enumerator>
            <enumerator name="GT_PEN_PRESSANDHOLD" access="">
                <type primitive="False">int</type>
                <value>
                    <code>3
        </code>
                </value>
            </enumerator>
            <enumerator name="GT_PEN_PRESSANDHOLDABORT" access="">
                <type primitive="False">int</type>
                <value>
                    <code>4
        </code>
                </value>
            </enumerator>
            <enumerator name="GT_TOUCH_TAP" access="">
                <type primitive="False">int</type>
                <value>
                    <code>5
        </code>
                </value>
            </enumerator>
            <enumerator name="GT_TOUCH_DOUBLETAP" access="">
                <type primitive="False">int</type>
                <value>
                    <code>6
        </code>
                </value>
            </enumerator>
            <enumerator name="GT_TOUCH_RIGHTTAP" access="">
                <type primitive="False">int</type>
                <value>
                    <code>7
        </code>
                </value>
            </enumerator>
            <enumerator name="GT_TOUCH_PRESSANDHOLD" access="">
                <type primitive="False">int</type>
                <value>
                    <code>8
        </code>
                </value>
            </enumerator>
            <enumerator name="GT_TOUCH_PRESSANDHOLDABORT" access="">
                <type primitive="False">int</type>
                <value>
                    <code>9
        </code>
                </value>
            </enumerator>
            <enumerator name="GT_TOUCH_PRESSANDTAP" access="">
                <type primitive="False">int</type>
                <value>
                    <code>10
        </code>
                </value>
            </enumerator>
        </enumeration>
    </namespace>
</bindings>
