<?xml version="1.0" encoding="UTF-8" standalone="yes" ?>
<bindings>
    <comment>
        // Copyright © Tanner Gooding and Contributors. Licensed under the MIT License (MIT). See License.md in the repository root for more information.
        
        // Ported from um/sapi.h in the Windows SDK for Windows 10.0.19041.0
        // Original source is Copyright © Microsoft. All rights reserved.
        
    </comment>
    <namespace name="TerraFX.Interop">
        <enumeration name="DISPID_SpeechLexicon" access="public">
            <type>int</type>
            <enumerator name="DISPID_SLGenerationId" access="">
                <type primitive="False">int</type>
                <value>
                    <code>1
        </code>
                </value>
            </enumerator>
            <enumerator name="DISPID_SLGetWords" access="">
                <type primitive="False">int</type>
                <value>
                    <code>(DISPID_SLGenerationId + 1)
        </code>
                </value>
            </enumerator>
            <enumerator name="DISPID_SLAddPronunciation" access="">
                <type primitive="False">int</type>
                <value>
                    <code>(DISPID_SLGetWords + 1)
        </code>
                </value>
            </enumerator>
            <enumerator name="DISPID_SLAddPronunciationByPhoneIds" access="">
                <type primitive="False">int</type>
                <value>
                    <code>(DISPID_SLAddPronunciation + 1)
        </code>
                </value>
            </enumerator>
            <enumerator name="DISPID_SLRemovePronunciation" access="">
                <type primitive="False">int</type>
                <value>
                    <code>(DISPID_SLAddPronunciationByPhoneIds + 1)
        </code>
                </value>
            </enumerator>
            <enumerator name="DISPID_SLRemovePronunciationByPhoneIds" access="">
                <type primitive="False">int</type>
                <value>
                    <code>(DISPID_SLRemovePronunciation + 1)
        </code>
                </value>
            </enumerator>
            <enumerator name="DISPID_SLGetPronunciations" access="">
                <type primitive="False">int</type>
                <value>
                    <code>(DISPID_SLRemovePronunciationByPhoneIds + 1)
        </code>
                </value>
            </enumerator>
            <enumerator name="DISPID_SLGetGenerationChange" access="">
                <type primitive="False">int</type>
                <value>
                    <code>(DISPID_SLGetPronunciations + 1)
        </code>
                </value>
            </enumerator>
        </enumeration>
    </namespace>
</bindings>
