<?xml version="1.0" encoding="UTF-8" standalone="yes" ?>
<bindings>
    <comment>
        // Copyright © Tanner Gooding and Contributors. Licensed under the MIT License (MIT). See License.md in the repository root for more information.
        
        // Ported from um/sapi.h in the Windows SDK for Windows 10.0.19041.0
        // Original source is Copyright © Microsoft. All rights reserved.
        
    </comment>
    <namespace name="TerraFX.Interop">
        <enumeration name="SPFILEMODE" access="public">
            <type>int</type>
            <enumerator name="SPFM_OPEN_READONLY" access="">
                <type primitive="False">int</type>
                <value>
                    <code>0
        </code>
                </value>
            </enumerator>
            <enumerator name="SPFM_OPEN_READWRITE" access="">
                <type primitive="False">int</type>
                <value>
                    <code>(SPFM_OPEN_READONLY + 1)
        </code>
                </value>
            </enumerator>
            <enumerator name="SPFM_CREATE" access="">
                <type primitive="False">int</type>
                <value>
                    <code>(SPFM_OPEN_READWRITE + 1)
        </code>
                </value>
            </enumerator>
            <enumerator name="SPFM_CREATE_ALWAYS" access="">
                <type primitive="False">int</type>
                <value>
                    <code>(SPFM_CREATE + 1)
        </code>
                </value>
            </enumerator>
            <enumerator name="SPFM_NUM_MODES" access="">
                <type primitive="False">int</type>
                <value>
                    <code>(SPFM_CREATE_ALWAYS + 1)
        </code>
                </value>
            </enumerator>
        </enumeration>
    </namespace>
</bindings>
