<?xml version="1.0" encoding="UTF-8" standalone="yes" ?>
<bindings>
    <comment>
        // Copyright © Tanner Gooding and Contributors. Licensed under the MIT License (MIT). See License.md in the repository root for more information.
        
        // Ported from um/DirectML.h in the Windows SDK for Windows 10.0.19041.0
        // Original source is Copyright © Microsoft. All rights reserved.
        
    </comment>
    <namespace name="TerraFX.Interop">
        <struct name="DML_BUFFER_TENSOR_DESC" access="public" unsafe="true">
            <field name="DataType" access="public">
                <type native="">DML_TENSOR_DATA_TYPE</type>
            </field>
            <field name="Flags" access="public">
                <type native="">DML_TENSOR_FLAGS</type>
            </field>
            <field name="DimensionCount" access="public">
                <type native="UINT">uint</type>
            </field>
            <field name="Sizes" access="public">
                <type native="const UINT *">uint*</type>
            </field>
            <field name="Strides" access="public">
                <type native="const UINT *">uint*</type>
            </field>
            <field name="TotalTensorSizeInBytes" access="public">
                <type native="UINT64">ulong</type>
            </field>
            <field name="GuaranteedBaseOffsetAlignment" access="public">
                <type native="UINT">uint</type>
            </field>
        </struct>
    </namespace>
</bindings>
