<?xml version="1.0" encoding="UTF-8" standalone="yes" ?>
<bindings>
    <comment>
        // Copyright © Tanner Gooding and Contributors. Licensed under the MIT License (MIT). See License.md in the repository root for more information.
        
        // Ported from um/imapi2.h in the Windows SDK for Windows 10.0.19041.0
        // Original source is Copyright © Microsoft. All rights reserved.
        
    </comment>
    <namespace name="TerraFX.Interop">
        <enumeration name="IMAPI_MODE_PAGE_TYPE" access="public">
            <type>int</type>
            <enumerator name="IMAPI_MODE_PAGE_TYPE_READ_WRITE_ERROR_RECOVERY" access="">
                <type primitive="False">int</type>
                <value>
                    <code>0x1
        </code>
                </value>
            </enumerator>
            <enumerator name="IMAPI_MODE_PAGE_TYPE_MRW" access="">
                <type primitive="False">int</type>
                <value>
                    <code>0x3
        </code>
                </value>
            </enumerator>
            <enumerator name="IMAPI_MODE_PAGE_TYPE_WRITE_PARAMETERS" access="">
                <type primitive="False">int</type>
                <value>
                    <code>0x5
        </code>
                </value>
            </enumerator>
            <enumerator name="IMAPI_MODE_PAGE_TYPE_CACHING" access="">
                <type primitive="False">int</type>
                <value>
                    <code>0x8
        </code>
                </value>
            </enumerator>
            <enumerator name="IMAPI_MODE_PAGE_TYPE_INFORMATIONAL_EXCEPTIONS" access="">
                <type primitive="False">int</type>
                <value>
                    <code>0x1c
        </code>
                </value>
            </enumerator>
            <enumerator name="IMAPI_MODE_PAGE_TYPE_TIMEOUT_AND_PROTECT" access="">
                <type primitive="False">int</type>
                <value>
                    <code>0x1d
        </code>
                </value>
            </enumerator>
            <enumerator name="IMAPI_MODE_PAGE_TYPE_POWER_CONDITION" access="">
                <type primitive="False">int</type>
                <value>
                    <code>0x1a
        </code>
                </value>
            </enumerator>
            <enumerator name="IMAPI_MODE_PAGE_TYPE_LEGACY_CAPABILITIES" access="">
                <type primitive="False">int</type>
                <value>
                    <code>0x2a
        </code>
                </value>
            </enumerator>
        </enumeration>
    </namespace>
</bindings>
