<?xml version="1.0" encoding="UTF-8" standalone="yes" ?>
<bindings>
    <comment>
        // Copyright © Tanner Gooding and Contributors. Licensed under the MIT License (MIT). See License.md in the repository root for more information.
        
        // Ported from um/wincodec.h in the Windows SDK for Windows 10.0.19041.0
        // Original source is Copyright © Microsoft. All rights reserved.
        
    </comment>
    <namespace name="TerraFX.Interop">
        <struct name="IWICComponentInfo" access="public" native="struct IWICComponentInfo : IUnknown" uuid="23bc3f0a-698b-4357-886b-f24d50671334" vtbl="true" unsafe="true">
            <field name="lpVtbl" access="public">
                <type native="">void**</type>
            </field>
            <function name="QueryInterface" access="public" unsafe="true">
                <type native="HRESULT">int</type>
                <param name="riid">
                    <type>Guid*</type>
                </param>
                <param name="ppvObject">
                    <type>void**</type>
                </param>
                <body>
                    <code>return ((delegate* unmanaged&lt;IWICComponentInfo*, Guid*, void**, int&gt;)(lpVtbl[<vtbl explicit="False">0</vtbl>]))(<param special="thisPtr">(IWICComponentInfo*)Unsafe.AsPointer(ref this)</param>, <param name="riid">riid</param>, <param name="ppvObject">ppvObject</param>);
        </code>
                </body>
            </function>
            <function name="AddRef" access="public" unsafe="true">
                <type native="ULONG">uint</type>
                <body>
                    <code>return ((delegate* unmanaged&lt;IWICComponentInfo*, uint&gt;)(lpVtbl[<vtbl explicit="False">1</vtbl>]))(<param special="thisPtr">(IWICComponentInfo*)Unsafe.AsPointer(ref this)</param>);
        </code>
                </body>
            </function>
            <function name="Release" access="public" unsafe="true">
                <type native="ULONG">uint</type>
                <body>
                    <code>return ((delegate* unmanaged&lt;IWICComponentInfo*, uint&gt;)(lpVtbl[<vtbl explicit="False">2</vtbl>]))(<param special="thisPtr">(IWICComponentInfo*)Unsafe.AsPointer(ref this)</param>);
        </code>
                </body>
            </function>
            <function name="GetComponentType" access="public" unsafe="true">
                <type native="HRESULT">int</type>
                <param name="pType">
                    <type>WICComponentType*</type>
                </param>
                <body>
                    <code>return ((delegate* unmanaged&lt;IWICComponentInfo*, WICComponentType*, int&gt;)(lpVtbl[<vtbl explicit="False">3</vtbl>]))(<param special="thisPtr">(IWICComponentInfo*)Unsafe.AsPointer(ref this)</param>, <param name="pType">pType</param>);
        </code>
                </body>
            </function>
            <function name="GetCLSID" access="public" unsafe="true">
                <type native="HRESULT">int</type>
                <param name="pclsid">
                    <type>Guid*</type>
                </param>
                <body>
                    <code>return ((delegate* unmanaged&lt;IWICComponentInfo*, Guid*, int&gt;)(lpVtbl[<vtbl explicit="False">4</vtbl>]))(<param special="thisPtr">(IWICComponentInfo*)Unsafe.AsPointer(ref this)</param>, <param name="pclsid">pclsid</param>);
        </code>
                </body>
            </function>
            <function name="GetSigningStatus" access="public" unsafe="true">
                <type native="HRESULT">int</type>
                <param name="pStatus">
                    <type>uint*</type>
                </param>
                <body>
                    <code>return ((delegate* unmanaged&lt;IWICComponentInfo*, uint*, int&gt;)(lpVtbl[<vtbl explicit="False">5</vtbl>]))(<param special="thisPtr">(IWICComponentInfo*)Unsafe.AsPointer(ref this)</param>, <param name="pStatus">pStatus</param>);
        </code>
                </body>
            </function>
            <function name="GetAuthor" access="public" unsafe="true">
                <type native="HRESULT">int</type>
                <param name="cchAuthor">
                    <type>uint</type>
                </param>
                <param name="wzAuthor">
                    <type>ushort*</type>
                </param>
                <param name="pcchActual">
                    <type>uint*</type>
                </param>
                <body>
                    <code>return ((delegate* unmanaged&lt;IWICComponentInfo*, uint, ushort*, uint*, int&gt;)(lpVtbl[<vtbl explicit="False">6</vtbl>]))(<param special="thisPtr">(IWICComponentInfo*)Unsafe.AsPointer(ref this)</param>, <param name="cchAuthor">cchAuthor</param>, <param name="wzAuthor">wzAuthor</param>, <param name="pcchActual">pcchActual</param>);
        </code>
                </body>
            </function>
            <function name="GetVendorGUID" access="public" unsafe="true">
                <type native="HRESULT">int</type>
                <param name="pguidVendor">
                    <type>Guid*</type>
                </param>
                <body>
                    <code>return ((delegate* unmanaged&lt;IWICComponentInfo*, Guid*, int&gt;)(lpVtbl[<vtbl explicit="False">7</vtbl>]))(<param special="thisPtr">(IWICComponentInfo*)Unsafe.AsPointer(ref this)</param>, <param name="pguidVendor">pguidVendor</param>);
        </code>
                </body>
            </function>
            <function name="GetVersion" access="public" unsafe="true">
                <type native="HRESULT">int</type>
                <param name="cchVersion">
                    <type>uint</type>
                </param>
                <param name="wzVersion">
                    <type>ushort*</type>
                </param>
                <param name="pcchActual">
                    <type>uint*</type>
                </param>
                <body>
                    <code>return ((delegate* unmanaged&lt;IWICComponentInfo*, uint, ushort*, uint*, int&gt;)(lpVtbl[<vtbl explicit="False">8</vtbl>]))(<param special="thisPtr">(IWICComponentInfo*)Unsafe.AsPointer(ref this)</param>, <param name="cchVersion">cchVersion</param>, <param name="wzVersion">wzVersion</param>, <param name="pcchActual">pcchActual</param>);
        </code>
                </body>
            </function>
            <function name="GetSpecVersion" access="public" unsafe="true">
                <type native="HRESULT">int</type>
                <param name="cchSpecVersion">
                    <type>uint</type>
                </param>
                <param name="wzSpecVersion">
                    <type>ushort*</type>
                </param>
                <param name="pcchActual">
                    <type>uint*</type>
                </param>
                <body>
                    <code>return ((delegate* unmanaged&lt;IWICComponentInfo*, uint, ushort*, uint*, int&gt;)(lpVtbl[<vtbl explicit="False">9</vtbl>]))(<param special="thisPtr">(IWICComponentInfo*)Unsafe.AsPointer(ref this)</param>, <param name="cchSpecVersion">cchSpecVersion</param>, <param name="wzSpecVersion">wzSpecVersion</param>, <param name="pcchActual">pcchActual</param>);
        </code>
                </body>
            </function>
            <function name="GetFriendlyName" access="public" unsafe="true">
                <type native="HRESULT">int</type>
                <param name="cchFriendlyName">
                    <type>uint</type>
                </param>
                <param name="wzFriendlyName">
                    <type>ushort*</type>
                </param>
                <param name="pcchActual">
                    <type>uint*</type>
                </param>
                <body>
                    <code>return ((delegate* unmanaged&lt;IWICComponentInfo*, uint, ushort*, uint*, int&gt;)(lpVtbl[<vtbl explicit="False">10</vtbl>]))(<param special="thisPtr">(IWICComponentInfo*)Unsafe.AsPointer(ref this)</param>, <param name="cchFriendlyName">cchFriendlyName</param>, <param name="wzFriendlyName">wzFriendlyName</param>, <param name="pcchActual">pcchActual</param>);
        </code>
                </body>
            </function>
        </struct>
    </namespace>
</bindings>
