<?xml version="1.0" encoding="UTF-8" standalone="yes" ?>
<bindings>
    <comment>
        // Copyright © Tanner Gooding and Contributors. Licensed under the MIT License (MIT). See License.md in the repository root for more information.
        
        // Ported from um/mfsharingengine.h in the Windows SDK for Windows 10.0.19041.0
        // Original source is Copyright © Microsoft. All rights reserved.
        
    </comment>
    <namespace name="TerraFX.Interop">
        <class name="Windows" access="public" static="true">
            <constant name="MF_MEDIA_SHARING_ENGINE_DEVICE_NAME" access="public">
                <type primitive="False">Guid</type>
                <value>
                    <code>new Guid(0x771e05d1, 0x862f, 0x4299, 0x95, 0xac, 0xae, 0x81, 0xfd, 0x14, 0xf3, 0xe7)
            </code>
                </value>
            </constant>
            <constant name="MF_MEDIA_SHARING_ENGINE_DEVICE" access="public">
                <type primitive="False">Guid</type>
                <value>
                    <code>new Guid(0xb461c58a, 0x7a08, 0x4b98, 0x99, 0xa8, 0x70, 0xfd, 0x5f, 0x3b, 0xad, 0xfd)
            </code>
                </value>
            </constant>
            <constant name="MF_MEDIA_SHARING_ENGINE_INITIAL_SEEK_TIME" access="public">
                <type primitive="False">Guid</type>
                <value>
                    <code>new Guid(0x6f3497f5, 0xd528, 0x4a4f, 0x8d, 0xd7, 0xdb, 0x36, 0x65, 0x7e, 0xc4, 0xc9)
            </code>
                </value>
            </constant>
            <constant name="MF_SHUTDOWN_RENDERER_ON_ENGINE_SHUTDOWN" access="public">
                <type primitive="False">Guid</type>
                <value>
                    <code>new Guid(0xc112d94d, 0x6b9c, 0x48f8, 0xb6, 0xf9, 0x79, 0x50, 0xff, 0x9a, 0xb7, 0x1e)
            </code>
                </value>
            </constant>
            <constant name="MF_PREFERRED_SOURCE_URI" access="public">
                <type primitive="False">Guid</type>
                <value>
                    <code>new Guid(0x5fc85488, 0x436a, 0x4db8, 0x90, 0xaf, 0x4d, 0xb4, 0x2, 0xae, 0x5c, 0x57)
            </code>
                </value>
            </constant>
            <constant name="MF_SHARING_ENGINE_SHAREDRENDERER" access="public">
                <type primitive="False">Guid</type>
                <value>
                    <code>new Guid(0xefa446a0, 0x73e7, 0x404e, 0x8a, 0xe2, 0xfe, 0xf6, 0x0a, 0xf5, 0xa3, 0x2b)
            </code>
                </value>
            </constant>
            <constant name="MF_SHARING_ENGINE_CALLBACK" access="public">
                <type primitive="False">Guid</type>
                <value>
                    <code>new Guid(0x57dc1e95, 0xd252, 0x43fa, 0x9b, 0xbc, 0x18, 0x0, 0x70, 0xee, 0xfe, 0x6d)
            </code>
                </value>
            </constant>
            <constant name="CLSID_MFMediaSharingEngineClassFactory" access="public">
                <type primitive="False">Guid</type>
                <value>
                    <code>new Guid(0xf8e307fb, 0x6d45, 0x4ad3, 0x99, 0x93, 0x66, 0xcd, 0x5a, 0x52, 0x96, 0x59)
            </code>
                </value>
            </constant>
            <constant name="CLSID_MFImageSharingEngineClassFactory" access="public">
                <type primitive="False">Guid</type>
                <value>
                    <code>new Guid(0xb22c3339, 0x87f3, 0x4059, 0xa0, 0xc5, 0x3, 0x7a, 0xa9, 0x70, 0x7e, 0xaf)
            </code>
                </value>
            </constant>
            <constant name="CLSID_PlayToSourceClassFactory" access="public">
                <type primitive="False">Guid</type>
                <value>
                    <code>new Guid(0xDA17539A, 0x3DC3, 0x42C1, 0xA7, 0x49, 0xA1, 0x83, 0xB5, 0x1F, 0x08, 0x5E)
            </code>
                </value>
            </constant>
            <constant name="GUID_PlayToService" access="public">
                <type primitive="False">Guid</type>
                <value>
                    <code>new Guid(0xf6a8ff9d, 0x9e14, 0x41c9, 0xbf, 0x0f, 0x12, 0x0a, 0x2b, 0x3c, 0xe1, 0x20)
            </code>
                </value>
            </constant>
            <constant name="GUID_NativeDeviceService" access="public">
                <type primitive="False">Guid</type>
                <value>
                    <code>new Guid(0xef71e53c, 0x52f4, 0x43c5, 0xb8, 0x6a, 0xad, 0x6c, 0xb2, 0x16, 0xa6, 0x1e)
            </code>
                </value>
            </constant>
            <iid name="IID_IMFSharingEngineClassFactory" value="0x2BA61F92, 0x8305, 0x413B, 0x97, 0x33, 0xFA, 0xF1, 0x5F, 0x25, 0x93, 0x84" />
            <iid name="IID_IMFMediaSharingEngine" value="0x8D3CE1BF, 0x2367, 0x40E0, 0x9E, 0xEE, 0x40, 0xD3, 0x77, 0xCC, 0x1B, 0x46" />
            <iid name="IID_IMFMediaSharingEngineClassFactory" value="0x524D2BC4, 0xB2B1, 0x4FE5, 0x8F, 0xAC, 0xFA, 0x4E, 0x45, 0x12, 0xB4, 0xE0" />
            <iid name="IID_IMFImageSharingEngine" value="0xCFA0AE8E, 0x7E1C, 0x44D2, 0xAE, 0x68, 0xFC, 0x4C, 0x14, 0x8A, 0x63, 0x54" />
            <iid name="IID_IMFImageSharingEngineClassFactory" value="0x1FC55727, 0xA7FB, 0x4FC8, 0x83, 0xAE, 0x8A, 0xF0, 0x24, 0x99, 0x0A, 0xF1" />
            <iid name="IID_IPlayToControl" value="0x607574EB, 0xF4B6, 0x45C1, 0xB0, 0x8C, 0xCB, 0x71, 0x51, 0x22, 0x90, 0x1D" />
            <iid name="IID_IPlayToControlWithCapabilities" value="0xAA9DD80F, 0xC50A, 0x4220, 0x91, 0xC1, 0x33, 0x22, 0x87, 0xF8, 0x2A, 0x34" />
            <iid name="IID_IPlayToSourceClassFactory" value="0x842B32A3, 0x9B9B, 0x4D1C, 0xB3, 0xF3, 0x49, 0x19, 0x32, 0x48, 0xA5, 0x54" />
        </class>
    </namespace>
</bindings>
